{
    "psi3": {
        "citation_count": 304,
        "most_recent": {
            "authors": "R Hellmann, C Gaiser, B Fellmuth\u2026\u00a0- The Journal of\u00a0\u2026, 2021 - aip.scitation.org",
            "link": "https://aip.scitation.org/doi/abs/10.1063/5.0047999",
            "title": "Thermophysical properties of low-density neon gas from highly accurate first-principles calculations and dielectric-constant gas thermometry measurements"
        }
    },
    "psi4": {
        "citation_count": 794,
        "most_recent": {
            "authors": "R Benda, L Vidal, E Giner\u2026\u00a0- Journal of Chemical\u00a0\u2026, 2021 - hal.archives-ouvertes.fr",
            "link": "https://hal.archives-ouvertes.fr/hal-03228618/",
            "title": "Numerical methods for computing ROHF ground states. Part I: SCF algorithms"
        }
    },
    "psi41p1": {
        "citation_count": 730,
        "most_recent": {
            "authors": "K Takimiya, K Kanazawa, K Kawabata\u00a0- Crystal Growth & Design, 2021 - ACS Publications",
            "link": "https://pubs.acs.org/doi/abs/10.1021/acs.cgd.1c00347",
            "title": "Crystal Structures of \u03b2-Methylchalcogenated Tetrathienoacenes: From One-Dimensional \u03c0-Stacking to Sandwich Pitched \u03c0-Stacking Structure"
        }
    },
    "psi41p4": {
        "citation_count": 69,
        "most_recent": {
            "authors": "S Behnle, RF Fink\u00a0- Journal of Chemical Theory and Computation, 2021 - ACS Publications",
            "link": "https://pubs.acs.org/doi/abs/10.1021/acs.jctc.1c00280",
            "title": "OO-REMP: Approaching Chemical Accuracy with Second-Order Perturbation Theory"
        }
    },
    "psi4numpy": {
        "citation_count": 69,
        "most_recent": {
            "authors": "G Qin, G Qin\u00a0- Complexity, 2021 - hindawi.com",
            "link": "https://www.hindawi.com/journals/complexity/2021/5562136/",
            "title": "Virtual Reality Video Image Classification Based on Texture Features"
        }
    }
}