{
    "psi3": {
        "citation_count": 305,
        "most_recent": {
            "authors": "EM Honor\u00e9, E R\u00edos, DR Alcoba\u2026\u00a0- International Journal of\u00a0\u2026 - Wiley Online Library",
            "link": "https://onlinelibrary.wiley.com/doi/abs/10.1002/qua.26862",
            "title": "Exploiting the nearsightedness principle within the framework of the anti\u2010Hermitian contracted Schr\u00f6dinger equation"
        }
    },
    "psi4": {
        "citation_count": 844,
        "most_recent": {
            "authors": "MAA Ibrahim, YAM Mohamed, HSM Abd Elhafez\u2026\u00a0- Journal of Molecular\u00a0\u2026, 2021 - Elsevier",
            "link": "https://www.sciencedirect.com/science/article/pii/S1093326321002680",
            "title": "R\u2022-hole interactions of group IV-VII radical-containing molecules: A comparative study"
        }
    },
    "psi41p1": {
        "citation_count": 835,
        "most_recent": {
            "authors": "F Ballesteros, KU Lao\u00a0- Journal of Chemical Theory and\u00a0\u2026, 2021 - ACS Publications",
            "link": "https://pubs.acs.org/doi/abs/10.1021/acs.jctc.1c00765",
            "title": "Accelerating the Convergence of Self-Consistent Field Calculations Using the Many-Body Expansion"
        }
    },
    "psi41p4": {
        "citation_count": 133,
        "most_recent": {
            "authors": "P Bandyopadhyay, P Priya, M Sadhukhan - 2021 - chemrxiv.org",
            "link": "https://chemrxiv.org/engage/chemrxiv/article-details/61ab28dfa02d160db4e3858f",
            "title": "A simple fragment-based method for van der Waals corrections over density functional theory"
        }
    },
    "psi4numpy": {
        "citation_count": 81,
        "most_recent": {
            "authors": "F Pavo\u0161evi\u0107, S Hammes-Schiffer, A Rubio\u2026\u00a0- arXiv preprint arXiv\u00a0\u2026, 2021 - arxiv.org",
            "link": "https://arxiv.org/abs/2112.02138",
            "title": "Cavity-Modulated Proton Transfer Reactions"
        }
    }
}